django_mysql_replication/__init__.py
django_mysql_replication/admin.py
django_mysql_replication/apps.py
django_mysql_replication/models.py
django_mysql_replication/signals.py
django_mysql_replication/tests.py
django_mysql_replication/utils.py
django_mysql_replication/views.py
django_mysql_replication/management/__init__.py
django_mysql_replication/management/commands/__init__.py
django_mysql_replication/management/commands/listen.py
django_mysql_replication/migrations/__init__.py
django_mysql_replication-0.1.3.dist-info/LICENSE
django_mysql_replication-0.1.3.dist-info/METADATA
django_mysql_replication-0.1.3.dist-info/WHEEL
django_mysql_replication-0.1.3.dist-info/top_level.txt
django_mysql_replication-0.1.3.dist-info/RECORD
